rastereasy/__init__.py
rastereasy/rastereasy.py
rastereasy/utils.py
rastereasy-0.3.2.dist-info/licenses/LICENCE
rastereasy-0.3.2.dist-info/METADATA
rastereasy-0.3.2.dist-info/WHEEL
rastereasy-0.3.2.dist-info/top_level.txt
rastereasy-0.3.2.dist-info/RECORD
