Metadata-Version: 2.4
Name: rastereasy
Version: 0.3.2
Summary: A library to ease the manipulation of geospatial images
Author-email: Thomas Corpetti <thomas.corpetti@gmail.com>
License-Expression: MIT
Project-URL: Homepage, https://rastereasy.github.io/
Project-URL: Repository, https://github.com/pythonraster/rastereasy
Requires-Python: >=3.9
License-File: LICENCE
Requires-Dist: rasterio
Requires-Dist: geopandas
Requires-Dist: POT>=0.9.5
Requires-Dist: scikit-learn
Requires-Dist: matplotlib
Requires-Dist: ipywidgets
Requires-Dist: PyQt5
Requires-Dist: ipympl
Dynamic: license-file
